{
  "project_info": {
    "project_number": "248567726483",
    "project_id": "projet-e9263",
    "storage_bucket": "projet-e9263.firebasestorage.app"
  },
  "client": [
    {
      "client_info": {
        "mobilesdk_app_id": "1:248567726483:android:8f02a5a078d22892d9e866",
        "android_client_info": {
          "package_name": "com.example.untitled"
        }
      },
      "oauth_client": [],
      "api_key": [
        {
          "current_key": "AIzaSyBDWsXhSiAHGONn5uxr7W1Thfd8MMJTDSQ"
        }
      ],
      "services": {
        "appinvite_service": {
          "other_platform_oauth_client": []
        }
      }
    }
  ],
  "configuration_version": "1"
}